django_vue_generator/__init__.py
django_vue_generator/forms.py
django_vue_generator/management/__init__.py
django_vue_generator/management/commands/build_frontend.py
django_vue_generator/management/commands/generate_vue_form.py
django_vue_generator/management/commands/start_frontend.py
django_vue_generator/migrations/__init__.py
django_vue_generator/models.py
django_vue_generator/tests.py
django_vue_generator/urls.py
django_vue_generator/utils.py
django_vue_generator/views.py
django_vue_generator-0.1.0.dist-info/WHEEL
django_vue_generator-0.1.0.dist-info/METADATA
django_vue_generator-0.1.0.dist-info/RECORD
